eth_prototype-1.4.1.dist-info/licenses/AUTHORS.rst
eth_prototype-1.4.1.dist-info/licenses/LICENSE.txt
ethproto/__init__.py
ethproto/aa_bundler.py
ethproto/build_artifacts.py
ethproto/contracts.py
ethproto/defender_relay.py
ethproto/w3wrappers.py
ethproto/wadray.py
ethproto/wrappers.py
ethproto/test_utils/__init__.py
ethproto/test_utils/factories.py
ethproto/test_utils/hardhat.py
ethproto/test_utils/vcr_utils.py
eth_prototype-1.4.1.dist-info/METADATA
eth_prototype-1.4.1.dist-info/WHEEL
eth_prototype-1.4.1.dist-info/top_level.txt
eth_prototype-1.4.1.dist-info/RECORD
