Metadata-Version: 2.4
Name: eth-prototype
Version: 1.4.1
Summary: Prototype Ethereum Smart Contracts in Python
Home-page: https://github.com/gnarvaja/eth-prototype
Author: Guillermo M. Narvaja
Author-email: guillermo@ensuro.co
License: MIT
Project-URL: Documentation, https://pyscaffold.org/
Platform: any
Classifier: Development Status :: 4 - Beta
Classifier: Programming Language :: Python
Requires-Python: >=3.7
License-File: LICENSE.txt
License-File: AUTHORS.rst
Requires-Dist: m9g
Requires-Dist: environs
Requires-Dist: requests
Requires-Dist: hexbytes
Requires-Dist: importlib-metadata; python_version < "3.8"
Provides-Extra: web3
Requires-Dist: web3==7.*; extra == "web3"
Provides-Extra: defender
Requires-Dist: boto3; extra == "defender"
Provides-Extra: gmpy2
Requires-Dist: gmpy2; extra == "gmpy2"
Provides-Extra: testing
Requires-Dist: boto3; extra == "testing"
Requires-Dist: factory-boy; extra == "testing"
Requires-Dist: gmpy2; extra == "testing"
Requires-Dist: pytest; extra == "testing"
Requires-Dist: pytest-cov; extra == "testing"
Requires-Dist: pytest-mock; extra == "testing"
Requires-Dist: pytest-recording; extra == "testing"
Requires-Dist: responses; extra == "testing"
Requires-Dist: setuptools; extra == "testing"
Requires-Dist: web3[tester]==7.*; extra == "testing"
Dynamic: license-file
